wmain/__init__.py
wmain/common/__init__.py
wmain/common/http/__init__.py
wmain/common/http/ua.py
wmain/common/http/url.py
wmain/common/logging.py
wmain/common/models.py
wmain/common/utils/__init__.py
wmain/common/utils/mutree.py
wmain/core/__init__.py
wmain/core/http/__init__.py
wmain/core/http/api.py
wmain_base-0.1.1.dist-info/METADATA
wmain_base-0.1.1.dist-info/WHEEL
wmain_base-0.1.1.dist-info/RECORD
